acousticdistance/__init__.py
acousticdistance/distances.py
acousticdistance/mfcc_features.py
acousticdistance/wav2vec2_features.py
acousticdistance/whisper_features.py
acousticdistance-0.1.0.dist-info/LICENSE
acousticdistance-0.1.0.dist-info/METADATA
acousticdistance-0.1.0.dist-info/WHEEL
acousticdistance-0.1.0.dist-info/RECORD
